setup.py
hngoption/HNFiles.py
hngoption/HNP.py
hngoption/Heston and Nandi Parameter Estimation.py
hngoption/LogLikelihood.py
hngoption/NMFiles.py
hngoption.egg-info/PKG-INFO
hngoption.egg-info/SOURCES.txt
hngoption.egg-info/dependency_links.txt
hngoption.egg-info/not-zip-safe
hngoption.egg-info/top_level.txt