Metadata-Version: 1.0
Name: hngoption
Version: 0.2
Summary: Heston Nandi GARCH Option Pricing Model (2000)
Home-page: https://github.com/SW71X/hngoption/archive/2.tar.gz
Author: Dustin L. Zacharias
Author-email: dustinl.zacharias@gmail.com
License: MIT
Platform: UNKNOWN
